labs/05-4bit-up-counter/rtl/up_counter_4bit.v
`timescale 1ns/1ps

module up_counter_4bit (
    input clk,
    input reset,
    output reg [3:0] count
);

always @(posedge clk or posedge reset) begin
    if (reset)
        count <= 4'b0000;
    else
        count <= count + 1'b1;
end

endmodule

labs/05-4bit-up-counter/tb/up_counter_4bit_tb.v
`timescale 1ns/1ps

module up_counter_4bit_tb;

reg clk;
reg reset;
wire [3:0] count;

up_counter_4bit uut (
    .clk(clk),
    .reset(reset),
    .count(count)
);

// 10 ns clock period
always #5 clk = ~clk;

initial begin
    $monitor("time=%0t reset=%b count=%b",
             $time, reset, count);

    clk = 0;
    reset = 1;

    // Asynchronous reset
    #10;
    reset = 0;

    // Allow counter to run through multiple cycles
    #170;

    // Test asynchronous reset again
    reset = 1;
    #7;
    reset = 0;

    #20;

    $finish;
end

initial begin
    $dumpfile("waveforms/up_counter_4bit.vcd");
    $dumpvars(0, up_counter_4bit_tb);
end

endmodule

labs/05-4bit-up-counter/waveforms/up_counter_4bit.vcd
$version Generated by VerilatedVcd $end
$timescale 1ps $end
 $scope module up_counter_4bit_tb $end
  $var wire 1 # clk $end
  $var wire 1 $ reset $end
  $var wire 4 % count [3:0] $end
  $scope module uut $end
   $var wire 1 # clk $end
   $var wire 1 $ reset $end
   $var wire 4 % count [3:0] $end
  $upscope $end
 $upscope $end
$enddefinitions $end


#0
0#
1$
b0000 %
#5000
1#
#10000
0#
0$
#15000
1#
b0001 %
#20000
0#
#25000
1#
b0010 %
#30000
0#
#35000
1#
b0011 %
#40000
0#
#45000
1#
b0100 %
#50000
0#
#55000
1#
b0101 %
#60000
0#
#65000
1#
b0110 %
#70000
0#
#75000
1#
b0111 %
#80000
0#
#85000
1#
b1000 %
#90000
0#
#95000
1#
b1001 %
#100000
0#
#105000
1#
b1010 %
#110000
0#
#115000
1#
b1011 %
#120000
0#
#125000
1#
b1100 %
#130000
0#
#135000
1#
b1101 %
#140000
0#
#145000
1#
b1110 %
#150000
0#
#155000
1#
b1111 %
#160000
0#
#165000
1#
b0000 %
#170000
0#
#175000
1#
b0001 %
#180000
0#
1$
b0000 %
#185000
1#
#187000
0$
#190000
0#
#195000
1#
b0001 %
#200000
0#
#205000
1#
b0010 %
