labs/07-ripple-up-counter/rtl/ripple_up_counter_4bit.v
`timescale 1ns/1ps

// T Flip-Flop
module tff (
    input clk,
    input reset,
    output reg q
);

always @(posedge clk or posedge reset) begin
    if (reset)
        q <= 1'b0;
    else
        q <= ~q;
end

endmodule


// 4-bit Ripple Up Counter
module ripple_up_counter_4bit (
    input clk,
    input reset,
    output [3:0] q
);

wire q_out0, q_out1, q_out2, q_out3;

assign q = {q_out3, q_out2, q_out1, q_out0};

// TFF instantiation
tff tff0 (
    .clk(clk),
    .reset(reset),
    .q(q_out0)
);

tff tff1 (
    .clk(~q_out0),
    .reset(reset),
    .q(q_out1)
);

tff tff2 (
    .clk(~q_out1),
    .reset(reset),
    .q(q_out2)
);

tff tff3 (
    .clk(~q_out2),
    .reset(reset),
    .q(q_out3)
);

endmodule

labs/07-ripple-up-counter/tb/ripple_up_counter_4bit_tb.v
`timescale 1ns/1ps

module ripple_up_counter_tb;

reg clk;
reg reset;
wire [3:0] q;

ripple_up_counter_4bit uut (
    .clk(clk),
    .reset(reset),
    .q(q)
);

// 10 ns clock period
always #5 clk = ~clk;

initial begin
    $display("Time\treset\tq");
    $monitor("%0dns\t%b\t%b", $time, reset, q);

    clk = 0;
    reset = 1;

    // Apply reset
    #10;
    reset = 0;

    // Allow counter to run
    #200;

    $finish;
end

initial begin
    $dumpfile("waveforms/ripple_up_counter_4bit.vcd");
    $dumpvars(0, ripple_up_counter_tb);
end

endmodule

labs/07-ripple-up-counter/waveforms/ripple_up_counter_4bit.vcd
$version Generated by VerilatedVcd $end
$timescale 1ps $end
 $scope module ripple_up_counter_tb $end
  $var wire 1 # clk $end
  $var wire 1 $ reset $end
  $var wire 4 % q [3:0] $end
  $scope module uut $end
   $var wire 1 # clk $end
   $var wire 1 $ reset $end
   $var wire 4 % q [3:0] $end
   $var wire 1 & q_out0 $end
   $var wire 1 ' q_out1 $end
   $var wire 1 ( q_out2 $end
   $var wire 1 ) q_out3 $end
   $scope module tff0 $end
    $var wire 1 # clk $end
    $var wire 1 $ reset $end
    $var wire 1 & q $end
   $upscope $end
   $scope module tff1 $end
    $var wire 1 * clk $end
    $var wire 1 $ reset $end
    $var wire 1 ' q $end
   $upscope $end
   $scope module tff2 $end
    $var wire 1 + clk $end
    $var wire 1 $ reset $end
    $var wire 1 ( q $end
   $upscope $end
   $scope module tff3 $end
    $var wire 1 , clk $end
    $var wire 1 $ reset $end
    $var wire 1 ) q $end
   $upscope $end
  $upscope $end
 $upscope $end
$enddefinitions $end


#0
0#
1$
b0000 %
0&
0'
0(
0)
1*
1+
1,
#5000
1#
#10000
0#
0$
#15000
1#
b0001 %
1&
0*
#20000
0#
#25000
1#
b0010 %
0&
1'
1*
0+
#30000
0#
#35000
1#
b0011 %
1&
0*
#40000
0#
#45000
1#
b0100 %
0&
0'
1(
1*
1+
0,
#50000
0#
#55000
1#
b0101 %
1&
0*
#60000
0#
#65000
1#
b0110 %
0&
1'
1*
0+
#70000
0#
#75000
1#
b0111 %
1&
0*
#80000
0#
#85000
1#
b1000 %
0&
0'
0(
1)
1*
1+
1,
#90000
0#
#95000
1#
b1001 %
1&
0*
#100000
0#
#105000
1#
b1010 %
0&
1'
1*
0+
#110000
0#
#115000
1#
b1011 %
1&
0*
#120000
0#
#125000
1#
b1100 %
0&
0'
1(
1*
1+
0,
#130000
0#
#135000
1#
b1101 %
1&
0*
#140000
0#
#145000
1#
b1110 %
0&
1'
1*
0+
#150000
0#
#155000
1#
b1111 %
1&
0*
#160000
0#
#165000
1#
b0000 %
0&
0'
0(
0)
1*
1+
1,
#170000
0#
#175000
1#
b0001 %
1&
0*
#180000
0#
#185000
1#
b0010 %
0&
1'
1*
0+
#190000
0#
#195000
1#
b0011 %
1&
0*
#200000
0#
#205000
1#
b0100 %
0&
0'
1(
1*
1+
0,
