labs/04-jk-flip-flop/rtl/jk_ff.v
`timescale 1ns/1ps

module jk_ff (
    input preset,   // Asynchronous active-high reset
    input clk,
    input j,
    input k,
    output reg q,
    output qn
);

assign qn = ~q;

always @(posedge clk or posedge preset) begin
    if (preset)
        q <= 1'b0;
    else begin
        case ({j, k})
            2'b00: q <= q;       // Hold
            2'b01: q <= 1'b0;    // Reset
            2'b10: q <= 1'b1;    // Set
            2'b11: q <= ~q;      // Toggle
        endcase
    end
end

endmodule

labs/04-jk-flip-flop/tb/jk_ff_tb.v
`timescale 1ns/1ps

module jk_ff_tb;

reg preset;
reg clk;
reg j, k;

wire q;
wire qn;

jk_ff dut (
    .preset(preset),
    .clk(clk),
    .j(j),
    .k(k),
    .q(q),
    .qn(qn)
);

// Clock generation: 10 ns period
always #5 clk = ~clk;

initial begin
    $monitor("%0t | preset=%b j=%b k=%b | q=%b qn=%b",
             $time, preset, j, k, q, qn);

    // Initial values
    clk = 0;
    preset = 1;
    j = 0;
    k = 0;

    // Hold reset
    #7;
    preset = 0;

    // Hold
    #10 j = 0; k = 0;

    // Reset
    #10 j = 0; k = 1;

    // Set
    #10 j = 1; k = 0;

    // Toggle
    #10 j = 1; k = 1;

    // Toggle again
    #10 j = 1; k = 1;

    // Assert asynchronous reset in middle of clock cycle
    #3 preset = 1;
    #4 preset = 0;

    #20;
    $finish;
end

initial begin
    $dumpfile("waveforms/jk_ff_async.vcd");
    $dumpvars(0, jk_ff_tb);
end

endmodule

labs/04-jk-flip-flop/waveforms/jk_ff_async.vcd
$version Generated by VerilatedVcd $end
$timescale 1ps $end
 $scope module jk_ff_tb $end
  $var wire 1 # preset $end
  $var wire 1 $ clk $end
  $var wire 1 % j $end
  $var wire 1 & k $end
  $var wire 1 ' q $end
  $var wire 1 ( qn $end
  $scope module dut $end
   $var wire 1 # preset $end
   $var wire 1 $ clk $end
   $var wire 1 % j $end
   $var wire 1 & k $end
   $var wire 1 ' q $end
   $var wire 1 ( qn $end
  $upscope $end
 $upscope $end
$enddefinitions $end


#0
1#
0$
0%
0&
0'
1(
#5000
1$
#7000
0#
#10000
0$
#15000
1$
#20000
0$
#25000
1$
#27000
1&
#30000
0$
#35000
1$
#37000
1%
0&
#40000
0$
#45000
1$
1'
0(
#47000
1&
#50000
0$
#55000
1$
0'
1(
#60000
1#
0$
#64000
0#
#65000
1$
1'
0(
#70000
0$
#75000
1$
0'
1(
