labs/09-apb-timer/rtl/apb_timer.v
`timescale 1ns/1ps

module apb_timer #(
    parameter WIDTH = 8
)(
    input  wire             PCLK,
    input  wire             PRESETn,

    input  wire             PSEL,
    input  wire             PENABLE,
    input  wire             PWRITE,
    input  wire [7:0]       PADDR,
    input  wire [31:0]      PWDATA,
    output reg  [31:0]      PRDATA,

    output reg              timer_done
);

    // Internal timer registers
    reg [WIDTH-1:0] load_val;
    reg [WIDTH-1:0] count;
    reg             running;

    // ------------------------------------------------------------
    // APB write path
    // ------------------------------------------------------------
    // Valid APB write:
    // PSEL=1, PENABLE=1, PWRITE=1
    always @(posedge PCLK or negedge PRESETn) begin
        if (!PRESETn) begin
            load_val <= {WIDTH{1'b0}};
            running  <= 1'b0;
        end
        else if (PSEL && PENABLE && PWRITE) begin
            case (PADDR)
                8'h00: load_val <= PWDATA[WIDTH-1:0];

                8'h04: begin
                    running <= PWDATA[0];

                    if (PWDATA[0])
                        count <= load_val;
                end

                default: begin
                    load_val <= load_val;
                    running  <= running;
                end
            endcase
        end
    end

    // ------------------------------------------------------------
    // APB read path
    // ------------------------------------------------------------
    always @(*) begin
        PRDATA = 32'h00000000;

        if (PSEL && !PWRITE) begin
            case (PADDR)
                8'h00:
                    PRDATA = {{(32-WIDTH){1'b0}}, load_val};

                8'h04:
                    PRDATA = {31'b0, running};

                8'h08:
                    PRDATA = {31'b0, timer_done};

                default:
                    PRDATA = 32'h00000000;
            endcase
        end
    end

    // ------------------------------------------------------------
    // Timer logic
    // ------------------------------------------------------------
    always @(posedge PCLK or negedge PRESETn) begin
        if (!PRESETn) begin
            count      <= {WIDTH{1'b0}};
            timer_done <= 1'b0;
        end
        else begin
            timer_done <= 1'b0;

            if (running) begin
                if (count > 0) begin
                    count <= count - 1'b1;

                    if (count == 1) begin
                        timer_done <= 1'b1;
                        running    <= 1'b0;
                    end
                end
            end
        end
    end

endmodule

labs/09-apb-timer/tb/apb_timer_tb.v
`timescale 1ns/1ps

module apb_timer_tb;

    // APB interface signals
    reg         PCLK;
    reg         PRESETn;
    reg         PSEL;
    reg         PENABLE;
    reg         PWRITE;
    reg [7:0]   PADDR;
    reg [31:0]  PWDATA;

    wire [31:0] PRDATA;
    wire        timer_done;

    // DUT
    apb_timer uut (
        .PCLK       (PCLK),
        .PRESETn    (PRESETn),
        .PSEL       (PSEL),
        .PENABLE    (PENABLE),
        .PWRITE     (PWRITE),
        .PADDR      (PADDR),
        .PWDATA     (PWDATA),
        .PRDATA     (PRDATA),
        .timer_done (timer_done)
    );

    // Clock generation
    initial PCLK = 1'b0;
    always #5 PCLK = ~PCLK;

    // Monitor timer completion
    always @(posedge timer_done) begin
        $display("Time=%0t ns : TIMER DONE", $time);
    end

    // ------------------------------------------------------------
    // APB WRITE
    // ------------------------------------------------------------
    task apb_write;
        input [7:0]  addr;
        input [31:0] data;

        begin
            // Setup phase
            @(posedge PCLK);
            PSEL    = 1'b1;
            PWRITE  = 1'b1;
            PENABLE = 1'b0;
            PADDR   = addr;
            PWDATA  = data;

            // Access phase
            @(posedge PCLK);
            PENABLE = 1'b1;

            @(posedge PCLK);
            PSEL    = 1'b0;
            PENABLE = 1'b0;
            PWRITE  = 1'b0;
        end
    endtask

    // ------------------------------------------------------------
    // APB READ
    // ------------------------------------------------------------
    task apb_read;
        input [7:0] addr;

        begin
            // Setup phase
            @(posedge PCLK);
            PSEL    = 1'b1;
            PWRITE  = 1'b0;
            PENABLE = 1'b0;
            PADDR   = addr;

            // Access phase
            @(posedge PCLK);
            PENABLE = 1'b1;

            @(posedge PCLK);
            $display("Read [0x%0h] = %0d",
                     addr, PRDATA);

            PSEL    = 1'b0;
            PENABLE = 1'b0;
        end
    endtask

    // ------------------------------------------------------------
    // Test sequence
    // ------------------------------------------------------------
    initial begin

        $dumpfile("waveforms/apb_timer.vcd");
        $dumpvars(0, apb_timer_tb);

        // Initial values
        PSEL    = 1'b0;
        PENABLE = 1'b0;
        PWRITE  = 1'b0;
        PADDR   = 8'h00;
        PWDATA  = 32'h00000000;

        // Apply reset
        PRESETn = 1'b0;
        #10;
        PRESETn = 1'b1;

        // Program load value = 5
        apb_write(8'h00, 5);

        // Start timer
        apb_write(8'h04, 1);

        // Wait and read status
        #80;
        apb_read(8'h08);

        // Program load value = 3
        apb_write(8'h00, 3);

        // Start timer again
        apb_write(8'h04, 1);

        // Read status after delay
        #50;
        apb_read(8'h08);

        #50;
        $finish;

    end

endmodule

labs/09-apb-timer/waveforms/apb_timer.vcd
$version Generated by VerilatedVcd $end
$timescale 1ps $end
 $scope module apb_timer_tb $end
  $var wire 1 - PCLK $end
  $var wire 1 # PRESETn $end
  $var wire 1 $ PSEL $end
  $var wire 1 % PENABLE $end
  $var wire 1 & PWRITE $end
  $var wire 8 ' PADDR [7:0] $end
  $var wire 32 ( PWDATA [31:0] $end
  $var wire 32 . PRDATA [31:0] $end
  $var wire 1 ) timer_done $end
  $scope module uut $end
   $var wire 32 / WIDTH [31:0] $end
   $var wire 1 - PCLK $end
   $var wire 1 # PRESETn $end
   $var wire 1 $ PSEL $end
   $var wire 1 % PENABLE $end
   $var wire 1 & PWRITE $end
   $var wire 8 ' PADDR [7:0] $end
   $var wire 32 ( PWDATA [31:0] $end
   $var wire 32 . PRDATA [31:0] $end
   $var wire 1 ) timer_done $end
   $var wire 8 * load_val [7:0] $end
   $var wire 8 + count [7:0] $end
   $var wire 1 , running $end
  $upscope $end
 $upscope $end
$enddefinitions $end


#0
0#
0$
0%
0&
b00000000 '
b00000000000000000000000000000000 (
0)
b00000000 *
b00000000 +
0,
0-
b00000000000000000000000000000000 .
b00000000000000000000000000001000 /
#5000
1-
#10000
1#
0-
#15000
1$
1&
b00000000000000000000000000000101 (
1-
#20000
0-
#25000
1%
b00000101 *
1-
#30000
0-
#35000
0$
0%
0&
1-
#40000
0-
#45000
1$
1&
b00000100 '
b00000000000000000000000000000001 (
1-
#50000
0-
#55000
1%
b00000101 +
1,
1-
#60000
0-
#65000
0$
0%
0&
b00000100 +
1-
#70000
0-
#75000
b00000011 +
1-
#80000
0-
#85000
b00000010 +
1-
#90000
0-
#95000
b00000001 +
1-
#100000
0-
#105000
1)
b00000000 +
0,
1-
#110000
0-
#115000
0)
1-
#120000
0-
#125000
1-
#130000
0-
#135000
1-
#140000
0-
#145000
1-
#150000
0-
#155000
1$
b00001000 '
1-
#160000
0-
#165000
1%
1-
#170000
0-
#175000
0$
0%
1-
#180000
0-
#185000
1$
1&
b00000000 '
b00000000000000000000000000000011 (
1-
#190000
0-
#195000
1%
b00000011 *
1-
#200000
0-
#205000
0$
0%
0&
1-
#210000
0-
#215000
1$
1&
b00000100 '
b00000000000000000000000000000001 (
1-
#220000
0-
#225000
1%
b00000011 +
1,
1-
#230000
0-
#235000
0$
0%
0&
b00000010 +
1-
#240000
0-
#245000
b00000001 +
1-
#250000
0-
#255000
1)
b00000000 +
0,
1-
#260000
0-
#265000
0)
1-
#270000
0-
#275000
1-
#280000
0-
#285000
1-
#290000
0-
#295000
1$
b00001000 '
1-
#300000
0-
#305000
1%
1-
#310000
0-
#315000
0$
0%
1-
