labs/12-cdc-synchronizer/rtl/cdc_sync.v
`timescale 1ns/1ps

// 2-stage synchronizer module to handle asynchronous input

module cdc_synchronizer (
    input  wire clk,
    input  wire async_in,
    output reg  synced
);

    reg stage1;

    // Two-stage flip-flop chain for synchronization
    always @(posedge clk) begin
        stage1 <= async_in;
        synced <= stage1;
    end

endmodule

labs/12-cdc-synchronizer/cdc_sync_tb.v
`timescale 1ns/1ps

module cdc_sync_tb;

    reg clk = 0;
    reg async_in = 0;
    wire synced;

    // Clock generation: 10 ns period
    always #5 clk = ~clk;

    // Instantiate the DUT
    cdc_synchronizer uut (
        .clk      (clk),
        .async_in (async_in),
        .synced   (synced)
    );

    initial begin

        $dumpfile("waveforms/dump.vcd");
        $dumpvars(0, cdc_sync_tb);

        // Apply asynchronous transitions
        #12 async_in = 1;
        #7  async_in = 0;
        #6  async_in = 1;
        #9  async_in = 0;

        #50 $finish;

    end

endmodule

labs/12-cdc-synchronizer/waveforms/dump.vcd
$version Generated by VerilatedVcd $end
$timescale 1ps $end
 $scope module cdc_sync_tb $end
  $var wire 1 # clk $end
  $var wire 1 $ async_in $end
  $var wire 1 % synced $end
  $scope module uut $end
   $var wire 1 # clk $end
   $var wire 1 $ async_in $end
   $var wire 1 % synced $end
   $var wire 1 & stage1 $end
  $upscope $end
 $upscope $end
$enddefinitions $end


#0
0#
0$
0%
0&
#5000
1#
#10000
0#
#12000
1$
#15000
1#
1&
#19000
0$
#20000
0#
#25000
1#
1$
1%
#30000
0#
#34000
0$
#35000
1#
0&
#40000
0#
#45000
1#
0%
